tom_publications/__init__.py
tom_publications/admin.py
tom_publications/apps.py
tom_publications/forms.py
tom_publications/latex.py
tom_publications/models.py
tom_publications/tests.py
tom_publications/urls.py
tom_publications/views.py
tom_publications/migrations/0001_initial.py
tom_publications/migrations/__init__.py
tom_publications/processors/__init__.py
tom_publications/processors/observation_group_latex_processor.py
tom_publications/processors/target_list_latex_processor.py
tom_publications/templatetags/__init__.py
tom_publications/templatetags/publication_extras.py
tom_publications_base/__init__.py
tom_publications_base/asgi.py
tom_publications_base/settings.py
tom_publications_base/urls.py
tom_publications_base/wsgi.py
tom_publications-0.1.0.dist-info/LICENSE
tom_publications-0.1.0.dist-info/METADATA
tom_publications-0.1.0.dist-info/WHEEL
tom_publications-0.1.0.dist-info/top_level.txt
tom_publications-0.1.0.dist-info/RECORD
