Metadata-Version: 2.1
Name: tom-publications
Version: 0.1.0
Summary: Add-on module for TOM Toolkit LaTeX generation
Home-page: https://tomtoolkit.github.io
Author: TOM Toolkit Project
Author-email: dcollom@lco.global
License: UNKNOWN
Keywords: tomtoolkit,astronomy,astrophysics,cosmology,science,fits,observatory
Platform: UNKNOWN
Classifier: Development Status :: 3 - Alpha
Classifier: Intended Audience :: Science/Research
Classifier: License :: OSI Approved :: BSD License
Classifier: Operating System :: OS Independent
Classifier: Programming Language :: Python :: 3
Classifier: Programming Language :: Python :: 3.7
Classifier: Topic :: Scientific/Engineering :: Astronomy
Classifier: Topic :: Scientific/Engineering :: Physics
Requires-Dist: tomtoolkit (==2.0.0)
Provides-Extra: test
Requires-Dist: factory-boy (==3.1.0) ; extra == 'test'
